django_events_timetable/LICENSE
django_events_timetable/README.md
django_events_timetable/__init__.py
django_events_timetable/admin.py
django_events_timetable/apps.py
django_events_timetable/cms_plugin.py
django_events_timetable/cms_plugins.py
django_events_timetable/forms.py
django_events_timetable/models.py
django_events_timetable/tests.py
django_events_timetable/urls.py
django_events_timetable/utils.py
django_events_timetable/views.py
django_events_timetable/wagtail_hooks.py
django_events_timetable/migrations/__init__.py
django_events_timetable/static/django_events_timetable/css/styles.css
django_events_timetable/static/django_events_timetable/js/event_admin.js
django_events_timetable/templates/django_events_timetable/event_items.html
django_events_timetable/templatetags/__init__.py
django_events_timetable/templatetags/display_events_tag.py
django_events_timetable-1.0.2.dist-info/METADATA
django_events_timetable-1.0.2.dist-info/WHEEL
django_events_timetable-1.0.2.dist-info/top_level.txt
django_events_timetable-1.0.2.dist-info/RECORD
