Metadata-Version: 2.1
Name: django-events-timetable
Version: 1.0.2
Summary: Django Events Timetable is an app component offering easy integration with Django, Django CMS, and Wagtail CMS. It features a user-friendly interface for managing event items, customizable and responsive templates with Dark and Light themes, and a color picker for design personalization. Designed to complement any project seamlessly, it is also extendable and customizable to meet specific needs.
Home-page: https://github.com/dostogircse171/django_events_timetable
Author: Mohammad Golam Dostogir, Amit Kumar
Author-email: contact@dostogir.dev, amitmodi06@gmail.com
License: UNKNOWN
Project-URL: Source, https://github.com/dostogircse171/django_events_timetable
Project-URL: Tracker, https://github.com/dostogircse171/django_events_timetable/issues
Project-URL: Demo, https://eventdemoapp-ceaa9c531c9c.herokuapp.com/
Platform: UNKNOWN
Classifier: Programming Language :: Python :: 3
Classifier: Framework :: Django
Classifier: License :: OSI Approved :: MIT License
Classifier: Operating System :: OS Independent
Requires-Python: >=3.6
Requires-Dist: Django (>=3.0)
